algocraft/__init__.py
algocraft/binary_search.py
algocraft/bubble_sort.py
algocraft/dijkstra.py
algocraft/factorial.py
algocraft/fibonacci_nth.py
algocraft/fibonacci_sequence.py
algocraft/floyd_warshall.py
algocraft/heap_sort.py
algocraft/knapsack_branch_bound.py
algocraft/linear_search.py
algocraft/matrix_multiplication.py
algocraft/merge_sort.py
algocraft/n_queens.py
algocraft/quick_sort.py
algocraft/simplex.py
algocraft/strassen_matrix_multiplication.py
algocraft/topological_sort.py
algocraft/tower_of_hanoi.py
algocraft-0.2.6.dist-info/METADATA
algocraft-0.2.6.dist-info/WHEEL
algocraft-0.2.6.dist-info/top_level.txt
algocraft-0.2.6.dist-info/RECORD
