Metadata-Version: 2.1
Name: algocraft
Version: 0.2.6
Summary: A collection of classic algorithms in Python
Author: Leander
Author-email: your.email@example.com
Classifier: Programming Language :: Python :: 3
Classifier: Operating System :: OS Independent
Requires-Python: >=3.6
Requires-Dist: numpy
